banquet/__init__.py
banquet/bin.py
banquet/builder.py
banquet/gateway.py
banquet/handler.py
banquet/router.py
banquet/server.py
banquet-0.0.1.dist-info/entry_points.txt
banquet-0.0.1.dist-info/LICENSE.md
banquet-0.0.1.dist-info/WHEEL
banquet-0.0.1.dist-info/METADATA
banquet-0.0.1.dist-info/RECORD
