Metadata-Version: 2.1
Name: banquet
Version: 0.0.1
Summary: CLI tool for working with OpenAPI and Lambda functions
Home-page: https://github.com/boughtbymany/banquet
License: MIT
Keywords: OpenAPI,HTTP,Deverlopment Server,AWS Lambda
Author: Nick Snell
Author-email: nick.snell@manypets.com
Requires-Python: >=3.8,<4.0
Classifier: Development Status :: 3 - Alpha
Classifier: Environment :: Web Environment
Classifier: Intended Audience :: Developers
Classifier: License :: OSI Approved :: MIT License
Classifier: Programming Language :: Python
Classifier: Programming Language :: Python :: 3
Classifier: Programming Language :: Python :: 3.10
Classifier: Programming Language :: Python :: 3.8
Classifier: Programming Language :: Python :: 3.9
Classifier: Topic :: Internet :: WWW/HTTP
Classifier: Topic :: Internet :: WWW/HTTP :: HTTP Servers
Classifier: Topic :: Software Development :: Build Tools
Classifier: Topic :: Software Development :: Testing
Classifier: Topic :: Utilities
Requires-Dist: PyYAML (==6.0)
Project-URL: Documentation, https://github.com/boughtbymany/banquet
Project-URL: Repository, https://github.com/boughtbymany/banquet
